tew652brp/__init__.py
tew652brp/client.py
tew652brp/core/__init__.py
tew652brp/core/base.py
tew652brp/core/utils.py
tew652brp/core/access/__init__.py
tew652brp/core/access/virtual/__init__.py
tew652brp/core/access/virtual/acts.py
tew652brp/core/access/virtual/handler.py
tew652brp/core/access/virtual/types.py
tew652brp/core/login/__init__.py
tew652brp/core/login/acts.py
tew652brp/core/login/handler.py
tew652brp-0.0.4.dist-info/LICENCE
tew652brp-0.0.4.dist-info/METADATA
tew652brp-0.0.4.dist-info/WHEEL
tew652brp-0.0.4.dist-info/top_level.txt
tew652brp-0.0.4.dist-info/RECORD
