Metadata-Version: 2.1
Name: tew652brp
Version: 0.0.4
Summary: Interface for working with the TEW-652BRP router API 
Home-page: UNKNOWN
Author: fl0pp5
License: UNKNOWN
Project-URL: Documentation, https://tew-652brp.readthedocs.io/
Project-URL: Source, https://github.com/fl0pp5/TEW-652BRP
Platform: UNKNOWN
Classifier: License :: OSI Approved :: GNU General Public License v3 (GPLv3)
Classifier: Programming Language :: Python :: 3
Classifier: Programming Language :: Python :: 3.6
Classifier: Programming Language :: Python :: 3.7
Classifier: Programming Language :: Python :: 3.8
Classifier: Programming Language :: Python :: 3.9
License-File: LICENCE
Requires-Dist: requests (>=2.26.0)
